LLMscreen/__init__.py
LLMscreen-1.0.0.dist-info/LICENSE
LLMscreen-1.0.0.dist-info/METADATA
LLMscreen-1.0.0.dist-info/WHEEL
LLMscreen-1.0.0.dist-info/top_level.txt
LLMscreen-1.0.0.dist-info/RECORD
